LICENSE.txt
MANIFEST.in
README.md
setup.py
roomy/__init__.py
roomy/config.py
roomy/constants.py
roomy/game.py
roomy/methods.py
roomy/tagged.py
roomy.egg-info/PKG-INFO
roomy.egg-info/SOURCES.txt
roomy.egg-info/dependency_links.txt
roomy.egg-info/requires.txt
roomy.egg-info/top_level.txt
roomy/animations/__init__.py
roomy/animations/animation.py
roomy/animations/fileanimation.py
roomy/animations/repeatanimation.py
roomy/extensions/__init__.py
roomy/extensions/renderable/__init__.py
roomy/extensions/renderable/animated.py
roomy/extensions/renderable/hitboxed.py
roomy/handlers/__init__.py
roomy/handlers/animationhandler.py
roomy/handlers/customclasshandler.py
roomy/handlers/enums.py
roomy/handlers/gameeventhandler.py
roomy/handlers/hitboxhandler.py
roomy/hitboxes/__init__.py
roomy/hitboxes/hitbox.py
roomy/hitboxes/recurfacehitbox.py
roomy/renderables/__init__.py
roomy/renderables/entity.py
roomy/renderables/enums.py
roomy/renderables/renderable.py
roomy/renderables/room.py
roomy/renderables/screens/__init__.py
roomy/renderables/screens/screen.py
roomy/renderables/screens/world.py
roomy/stats/__init__.py
roomy/stats/genericstat.py
roomy/stats/methods.py
roomy/stats/stat.py